dhitools/__init__.py
dhitools/_gridded_interpolate.py
dhitools/_raster_interpolate.py
dhitools/_utils.py
dhitools/config.py
dhitools/dfs.py
dhitools/dfsu.py
dhitools/mesh.py
dhitools/units.py
dhitools-1.1.0.dist-info/METADATA
dhitools-1.1.0.dist-info/RECORD
dhitools-1.1.0.dist-info/WHEEL
dhitools-1.1.0.dist-info/top_level.txt
