Metadata-Version: 2.1
Name: dhitools
Version: 1.1.0
Summary: Python tools for working with DHI MIKE21
Home-page: https://github.com/robjameswall/dhitools
Author: Rob Wall
Author-email: rob.james.wall@gmail.com
License: LICENSE.txt
Platform: UNKNOWN
Classifier: Programming Language :: Python :: 2
Classifier: Programming Language :: Python :: 3
Classifier: Operating System :: Microsoft :: Windows
Classifier: License :: OSI Approved :: MIT License
Requires-Dist: numpy (>=1.14.5)
Requires-Dist: PyCRS (>=0.1.3)
Requires-Dist: scipy (>=1.1.0)
Requires-Dist: pandas (>=0.23.1)
